{
  "timestamp": 1769930720,
  "device_name": "HF15 Inverter 5",
  "device_id": "NE=50127680",
  "data": {
    "pv10_current": 9.2,
    "pv10_voltage": 727.1,
    "pv11_current": 0,
    "pv11_voltage": 93.4,
    "pv12_current": 0,
    "pv12_voltage": 93.4,
    "pv13_current": 0,
    "pv13_voltage": 706.4,
    "pv14_current": 9.52,
    "pv14_voltage": 706.4,
    "pv15_current": 0,
    "pv15_voltage": 737.7,
    "pv16_current": 9.27,
    "pv16_voltage": 737.7,
    "pv17_current": 0,
    "pv17_voltage": 742.1,
    "pv18_current": 8.82,
    "pv18_voltage": 742.1,
    "pv19_current": 0,
    "pv19_voltage": 727.2,
    "pv1_current": 0,
    "pv1_voltage": 726.7,
    "pv20_current": 8.63,
    "pv20_voltage": 727.2,
    "pv21_current": 0,
    "pv21_voltage": 0,
    "pv22_current": 0,
    "pv22_voltage": 0,
    "pv23_current": 0,
    "pv23_voltage": 0,
    "pv24_current": 0,
    "pv24_voltage": 0,
    "pv25_current": 0,
    "pv25_voltage": 0,
    "pv26_current": 0,
    "pv26_voltage": 0,
    "pv27_current": 0,
    "pv27_voltage": 0,
    "pv2_current": 9.04,
    "pv2_voltage": 726.7,
    "pv3_current": 0,
    "pv3_voltage": 713.4,
    "pv4_current": 8.96,
    "pv4_voltage": 713.4,
    "pv5_current": 0,
    "pv5_voltage": 718.3,
    "pv6_current": 9.4,
    "pv6_voltage": 718.3,
    "pv7_current": 0,
    "pv7_voltage": 724.4,
    "pv8_current": 9.19,
    "pv8_voltage": 724.4,
    "pv9_current": 0,
    "pv9_voltage": 727.1
  }
}