{
  "timestamp": 1769999407,
  "device_name": "HF1 Inverter 4",
  "device_id": "NE=50162857",
  "data": {
    "pv10_current": 7.53,
    "pv10_voltage": 752.8,
    "pv11_current": 0,
    "pv11_voltage": 106.7,
    "pv12_current": 0,
    "pv12_voltage": 106.7,
    "pv13_current": 0,
    "pv13_voltage": 762.9,
    "pv14_current": 7.32,
    "pv14_voltage": 762.9,
    "pv15_current": 0,
    "pv15_voltage": 752.4,
    "pv16_current": 7.58,
    "pv16_voltage": 752.4,
    "pv17_current": 0,
    "pv17_voltage": 739.8,
    "pv18_current": 7.55,
    "pv18_voltage": 739.8,
    "pv19_current": 0,
    "pv19_voltage": 728.3,
    "pv1_current": 0,
    "pv1_voltage": 759.1,
    "pv20_current": 7.26,
    "pv20_voltage": 728.3,
    "pv21_current": 0,
    "pv21_voltage": 0,
    "pv22_current": 0,
    "pv22_voltage": 0,
    "pv23_current": 0,
    "pv23_voltage": 0,
    "pv24_current": 0,
    "pv24_voltage": 0,
    "pv25_current": 0,
    "pv25_voltage": 0,
    "pv26_current": 0,
    "pv26_voltage": 0,
    "pv27_current": 0,
    "pv27_voltage": 0,
    "pv2_current": 7.38,
    "pv2_voltage": 759.1,
    "pv3_current": 0,
    "pv3_voltage": 757.5,
    "pv4_current": 7.3,
    "pv4_voltage": 757.5,
    "pv5_current": 0,
    "pv5_voltage": 763.7,
    "pv6_current": 7.46,
    "pv6_voltage": 763.7,
    "pv7_current": 0,
    "pv7_voltage": 754,
    "pv8_current": 7.55,
    "pv8_voltage": 754,
    "pv9_current": 0,
    "pv9_voltage": 752.8
  }
}