{
  "buildCode": "2",
  "data": [
    {
      "status": 1
    },
    {
      "groupName": "Others",
      "signals": [
        {
          "id": 10025,
          "latestTime": 1769849407,
          "name": "Inverter status",
          "realValue": "512",
          "unit": "",
          "value": "Grid connected"
        },
        {
          "id": 10032,
          "latestTime": 1769849407,
          "name": "Daily energy",
          "realValue": "180.32",
          "unit": "kWh",
          "value": "180.32"
        },
        {
          "id": 10029,
          "latestTime": 1769849407,
          "name": "Total yield",
          "realValue": "318404.26",
          "unit": "kWh",
          "value": "318404.26"
        },
        {
          "id": 10018,
          "latestTime": 1769849407,
          "name": "Active power",
          "realValue": "14.571",
          "unit": "kW",
          "value": "14.571"
        },
        {
          "id": 10019,
          "latestTime": 1769849407,
          "name": "Output reactive power",
          "realValue": "-0.063",
          "unit": "kvar",
          "value": "-0.063"
        },
        {
          "id": 10006,
          "latestTime": 1769820609,
          "name": "Inverter rated power",
          "realValue": "60.000",
          "unit": "kW",
          "value": "60.000"
        },
        {
          "id": 10020,
          "latestTime": 1769849407,
          "name": "Power factor",
          "realValue": "0.999",
          "unit": "",
          "value": "0.999"
        },
        {
          "id": 10021,
          "latestTime": 1769849407,
          "name": "Grid frequency",
          "realValue": "50.18",
          "unit": "Hz",
          "value": "50.18"
        },
        {
          "id": 21029,
          "latestTime": 1769820610,
          "name": "Output mode",
          "realValue": "0",
          "unit": "",
          "value": "Three-phase four-wire system"
        },
        {
          "id": 10014,
          "latestTime": 1769849407,
          "name": "Grid phase A current",
          "realValue": "21.695",
          "unit": "A",
          "value": "21.695"
        },
        {
          "id": 10015,
          "latestTime": 1769849407,
          "name": "Grid phase B current",
          "realValue": "21.762",
          "unit": "A",
          "value": "21.762"
        },
        {
          "id": 10016,
          "latestTime": 1769849407,
          "name": "Grid phase C current",
          "realValue": "21.659",
          "unit": "A",
          "value": "21.659"
        },
        {
          "id": 10011,
          "latestTime": 1769849407,
          "name": "Phase A voltage",
          "realValue": "223.7",
          "unit": "V",
          "value": "223.7"
        },
        {
          "id": 10012,
          "latestTime": 1769849407,
          "name": "Phase B voltage",
          "realValue": "223.4",
          "unit": "V",
          "value": "223.4"
        },
        {
          "id": 10013,
          "latestTime": 1769849407,
          "name": "Phase C voltage",
          "realValue": "226.4",
          "unit": "V",
          "value": "226.4"
        },
        {
          "id": 10027,
          "latestTime": 1769820609,
          "name": "Inverter startup time",
          "realValue": "2026-01-31 06:19:27",
          "unit": "",
          "value": "2026-01-31 06:19:27"
        },
        {
          "id": 10028,
          "latestTime": 1769820609,
          "name": "Inverter shutdown time",
          "realValue": "2026-01-30 18:12:31",
          "unit": "",
          "value": "2026-01-30 18:12:31"
        },
        {
          "id": 10023,
          "latestTime": 1769849407,
          "name": "Internal temperature",
          "realValue": "56.8",
          "unit": "℃",
          "value": "56.8"
        },
        {
          "id": 10024,
          "latestTime": 1769849407,
          "name": "Insulation resistance",
          "realValue": "7.920",
          "unit": "MΩ",
          "value": "7.920"
        },
        {
          "id": 230223000,
          "latestTime": 1769820610,
          "name": "Active power adjustment status",
          "realValue": "P=100.0% (Active power derating by percentage)",
          "unit": "",
          "value": "P=100.0% (Active power derating by percentage)"
        },
        {
          "id": 230223001,
          "latestTime": 1769847153,
          "name": "Reactive power adjustment status",
          "realValue": "Q/S=-0.001(Q/S adjustment)",
          "unit": "",
          "value": "Q/S=-0.001(Q/S adjustment)"
        }
      ]
    },
    {
      "pv2mppt": false
    }
  ],
  "failCode": 0,
  "params": [],
  "success": true
}